_examples/__init__.py
examples/__init__.py
sphinx_terminhtml/__init__.py
sphinx_terminhtml/assets.py
sphinx_terminhtml/cache.py
sphinx_terminhtml/directives.py
sphinx_terminhtml/get_version.py
sphinx_terminhtml/logger.py
sphinx_terminhtml/options.py
sphinx_terminhtml/sphinx_setup.py
sphinx_terminhtml/wipe_cache.py
tests/__init__.py
tests/test_placeholder.py
sphinx_terminhtml-1.4.0.dist-info/LICENSE.md
sphinx_terminhtml-1.4.0.dist-info/METADATA
sphinx_terminhtml-1.4.0.dist-info/WHEEL
sphinx_terminhtml-1.4.0.dist-info/top_level.txt
sphinx_terminhtml-1.4.0.dist-info/RECORD
