Metadata-Version: 2.1
Name: sphinx-terminhtml
Version: 1.4.0
Summary: Write bash commands in a Sphinx directive, output an animated HTML/CSS terminal
Home-page: https://github.com/nickderobertis/sphinx-terminhtml
Author: Nick DeRobertis
Author-email: derobertis.nick@gmail.com
License: MIT
Project-URL: Code, https://github.com/nickderobertis/sphinx-terminhtml
Project-URL: Documentation, https://nickderobertis.github.io/sphinx-terminhtml
Platform: UNKNOWN
Classifier: Development Status :: 3 - Alpha
Classifier: Intended Audience :: Developers
Classifier: Programming Language :: Python :: 3.6
Classifier: Programming Language :: Python :: 3.7
License-File: LICENSE.md
Requires-Dist: terminhtml (>=0.6.0)
Requires-Dist: requests
Requires-Dist: appdirs
